
{
  "name": "antarctica/trusty",
  "description": "A vanilla Ubuntu 14.04 LTS amd64 base box",
  "versions": [
    {
      "version": "0.1.0",
      "providers": [
        {
          "name": "virtualbox",
          "url": "https://s3-eu-west-1.amazonaws.com/packages.calcifer.co/vagrant/baseboxes/ubuntu/14.04/x64/virtualbox/0.1.0/ubuntu-14.04-64-basebox-virtualbox.box",
          "checksum_type": "sha1",
          "checksum": "4db63bb6306359cdede0c21b0e6b2292427f1a40"
        }
      ]
    },
    {
      "version": "0.1.1",
      "providers": [
        {
          "name": "virtualbox",
          "url": "https://s3-eu-west-1.amazonaws.com/packages.calcifer.co/vagrant/baseboxes/ubuntu/14.04/x64/virtualbox/0.1.1/ubuntu-14.04-64-basebox-virtualbox.box",
          "checksum_type": "sha1",
          "checksum": "9ca965a7ce94d8ae8dac57292f17671178ef64c1"
        }
      ]
    },
    {
      "version": "0.2.0",
      "providers": [
        {
          "name": "virtualbox",
          "url": "https://s3-eu-west-1.amazonaws.com/packages.calcifer.co/vagrant/baseboxes/ubuntu/14.04/x64/virtualbox/0.2.0/ubuntu-14.04-64-basebox-virtualbox.box",
          "checksum_type": "sha1",
          "checksum": "88978916d14bbdbf8e85c0d757978ef1778c6ae9"
        }
      ]
    },
    {
      "version": "0.3.0",
      "providers": [
        {
          "name": "virtualbox",
          "url": "https://s3-eu-west-1.amazonaws.com/packages.calcifer.co/vagrant/baseboxes/ubuntu/14.04/x64/virtualbox/0.3.0/ubuntu-14.04-64-basebox-virtualbox.box",
          "checksum_type": "sha1",
          "checksum": "4a92c57de017917045962d1bf45500a6f879ddc0"
        }
      ]
    },
    {
      "version": "0.4.0",
      "providers": [
        {
          "name": "virtualbox",
          "url": "https://s3-eu-west-1.amazonaws.com/packages.calcifer.co/vagrant/baseboxes/ubuntu/14.04/x64/virtualbox/0.4.0/ubuntu-14.04-64-basebox-virtualbox.box",
          "checksum_type": "sha1",
          "checksum": "bc300dbede62386545cc94e76b56a0606eeb89e7"
        }
      ]
    },
    {
      "version": "0.4.1",
      "providers": [
        {
          "name": "virtualbox",
          "url": "https://s3-eu-west-1.amazonaws.com/packages.calcifer.co/vagrant/baseboxes/ubuntu/14.04/x64/virtualbox/0.4.1/ubuntu-14.04-64-basebox-virtualbox.box",
          "checksum_type": "sha1",
          "checksum": "1a561a04cb7d12e08f76c736dff81f307f9db154"
        }
      ]
    },
    {
      "version": "0.4.2",
      "providers": [
        {
          "name": "virtualbox",
          "url": "https://s3-eu-west-1.amazonaws.com/packages.calcifer.co/vagrant/baseboxes/ubuntu/14.04/x64/virtualbox/0.4.2/ubuntu-14.04-64-basebox-virtualbox.box",
          "checksum_type": "sha1",
          "checksum": "c25770e62e4f83ae9b55e21e22462b7009654f5a"
        }
      ]
    },
    {
      "version": "0.4.3",
      "providers": [
        {
          "name": "virtualbox",
          "url": "https://s3-eu-west-1.amazonaws.com/packages.calcifer.co/vagrant/baseboxes/ubuntu/14.04/x64/virtualbox/0.4.3/ubuntu-14.04-64-basebox-virtualbox.box",
          "checksum_type": "sha1",
          "checksum": "68eb556988304476df33fe24e894ba5b060c47aa"
        },
        {
          "name": "vmware_desktop",
          "url": "https://s3-eu-west-1.amazonaws.com/packages.calcifer.co/vagrant/baseboxes/ubuntu/14.04/x64/vmware/0.4.3/ubuntu-14.04-64-basebox-vmware.box",
          "checksum_type": "sha1",
          "checksum": "9b2afc77a85b0037b33c00b581efb7a463b1e526"
        }
      ]
    },
    {
      "version": "0.4.4",
      "providers": [
        {
          "name": "virtualbox",
          "url": "https://s3-eu-west-1.amazonaws.com/packages.calcifer.co/vagrant/baseboxes/ubuntu/14.04/x64/virtualbox/0.4.4/ubuntu-14.04-64-virtualbox.box",
          "checksum_type": "sha1",
          "checksum": "0cd3292ea1fc607bf7c060ba671f5774d85a3b95"
        },
        {
          "name": "vmware_desktop",
          "url": "https://s3-eu-west-1.amazonaws.com/packages.calcifer.co/vagrant/baseboxes/ubuntu/14.04/x64/vmware/0.4.4/ubuntu-14.04-64-vmware.box",
          "checksum_type": "sha1",
          "checksum": "ac67d5502b75100253273677fc0d9a61082bef0f"
        }
      ]
    },
    {
      "version": "1.0.0",
      "providers": [
        {
          "name": "virtualbox",
          "url": "https://s3-eu-west-1.amazonaws.com/packages.calcifer.co/vagrant/baseboxes/ubuntu/14.04/amd64/1.0.0/virtualbox.box",
          "checksum_type": "sha1",
          "checksum": "ea1cd8d10c5eab0ed24756e32684b2426b8b18e0"
        },
        {
          "name": "vmware_desktop",
          "url": "https://s3-eu-west-1.amazonaws.com/packages.calcifer.co/vagrant/baseboxes/ubuntu/14.04/amd64/1.0.0/vmware.box",
          "checksum_type": "sha1",
          "checksum": "2a2d1532237ff02c1ce334545cb42dee1bc8c11b"
        }
      ]
    },
    {
      "version": "1.0.1",
      "providers": [
        {
          "name": "virtualbox",
          "url": "https://s3-eu-west-1.amazonaws.com/packages.calcifer.co/vagrant/baseboxes/ubuntu/14.04/amd64/1.0.1/virtualbox.box",
          "checksum_type": "sha1",
          "checksum": "df4422ac3da1bd6e684cf7d8343e6c9030c9e013"
        },
        {
          "name": "vmware_desktop",
          "url": "https://s3-eu-west-1.amazonaws.com/packages.calcifer.co/vagrant/baseboxes/ubuntu/14.04/amd64/1.0.1/vmware.box",
          "checksum_type": "sha1",
          "checksum": "517380914c84912904a48b76292438619deb0355"
        }
      ]
    },
    {
      "version": "1.1.0",
      "providers": [
        {
          "name": "virtualbox",
          "url": "https://s3-eu-west-1.amazonaws.com/packages.calcifer.co/vagrant/baseboxes/ubuntu/14.04/amd64/1.1.0/virtualbox.box",
          "checksum_type": "sha1",
          "checksum": "b541b94f5218a39b5868cd59d884b93f0e743365"
        },
        {
          "name": "vmware_desktop",
          "url": "https://s3-eu-west-1.amazonaws.com/packages.calcifer.co/vagrant/baseboxes/ubuntu/14.04/amd64/1.1.0/vmware.box",
          "checksum_type": "sha1",
          "checksum": "02ddb46bbe3631cba83a3535c59693eb54f28022"
        }
      ]
    },
    {
      "version": "1.2.0",
      "providers": [
        {
          "name": "virtualbox",
          "url": "https://s3-eu-west-1.amazonaws.com/packages.calcifer.co/vagrant/baseboxes/ubuntu/14.04/amd64/1.2.0/virtualbox.box",
          "checksum_type": "sha1",
          "checksum": "efd4c408ef51b20f25f70995fece8cb4cda20abc"
        },
        {
          "name": "vmware_desktop",
          "url": "https://s3-eu-west-1.amazonaws.com/packages.calcifer.co/vagrant/baseboxes/ubuntu/14.04/amd64/1.2.0/vmware.box",
          "checksum_type": "sha1",
          "checksum": "b6f999db47b5ded37a1a537ce4c1b005bf076ca4"
        }
      ]
    },
    {
      "version": "2.0.0",
      "providers": [
        {
          "name": "virtualbox",
          "url": "https://s3-eu-west-1.amazonaws.com/packages.calcifer.co/vagrant/baseboxes/ubuntu/14.04/amd64/2.0.0/virtualbox.box",
          "checksum_type": "sha1",
          "checksum": "e53a37dfecc3f071a41edf6adc03bb0d88f4a631"
        },
        {
          "name": "vmware_desktop",
          "url": "https://s3-eu-west-1.amazonaws.com/packages.calcifer.co/vagrant/baseboxes/ubuntu/14.04/amd64/2.0.0/vmware.box",
          "checksum_type": "sha1",
          "checksum": "17f5c1beedb4c4f473629c9c7f3be3ee3067fc82"
        }
      ]
    },
    {
      "version": "2.1.0",
      "providers": [
        {
          "name": "virtualbox",
          "url": "https://s3-eu-west-1.amazonaws.com/packages.calcifer.co/vagrant/baseboxes/ubuntu/14.04/amd64/2.1.0/virtualbox.box",
          "checksum_type": "sha1",
          "checksum": "9ab5c2cf9083d83f43ffda19bf27f1a497c7cc5d"
        },
        {
          "name": "vmware_desktop",
          "url": "https://s3-eu-west-1.amazonaws.com/packages.calcifer.co/vagrant/baseboxes/ubuntu/14.04/amd64/2.1.0/vmware.box",
          "checksum_type": "sha1",
          "checksum": "041aabae36a31d3148f92e398156dbaf8860d8a5"
        }
      ]
    },
    {
      "version": "3.0.0",
      "providers": [
        {
          "name": "virtualbox",
          "url": "https://s3-eu-west-1.amazonaws.com/packages.calcifer.co/vagrant/baseboxes/ubuntu/14.04/amd64/3.0.0/virtualbox.box",
          "checksum_type": "sha1",
          "checksum": "c9c826f02233967519a0e1bd8d15c8bfd720f181"
        },
        {
          "name": "vmware_desktop",
          "url": "https://s3-eu-west-1.amazonaws.com/packages.calcifer.co/vagrant/baseboxes/ubuntu/14.04/amd64/3.0.0/vmware.box",
          "checksum_type": "sha1",
          "checksum": "99ccf03c35d450a4b6d87a8dd9a61dc1619a479c"
        }
      ]
    }
  ]
}
